flask_super_macros/__init__.py
flask_super_macros/storybook.py
flask_super_macros-0.2.0.dist-info/WHEEL
flask_super_macros-0.2.0.dist-info/METADATA
flask_super_macros-0.2.0.dist-info/RECORD
