Metadata-Version: 2.4
Name: flask-super-macros
Version: 0.2.0
Summary: Super charged Jinja macros for Flask
Author: Maxime Bouroumeau-Fuseau
Author-email: Maxime Bouroumeau-Fuseau <maxime.bouroumeau@gmail.com>
License-Expression: MIT
Requires-Dist: flask>=3.0.0
Requires-Dist: jinja-super-macros>=0.1.0
Requires-Python: >=3.10
Project-URL: Repository, https://github.com/hyperflask/flask-super-macros
